{
    "url": "http://www.newrustacean.com/feed.xml",
    "title": "New Rustacean",
    "shortname": "newrust",
    "episodes": [
        {
            "url": "http://www.podtrac.com/pts/redirect.mp3/cdn.newrustacean.com/interview/rbr_2017/arun_kulshreshtha.mp3",
            "downloaded": true,
            "title": "RBR 2017: Arun Kulsheshthra",
            "published": 1510689771.0,
            "listened": false
        },
        {
            "url": "http://www.podtrac.com/pts/redirect.mp3/cdn.newrustacean.com/interview/rbr_2017/anthony_deschamps.mp3",
            "downloaded": true,
            "title": "RBR 2017: Anthony Deschamps",
            "published": 1510606956.0,
            "listened": false
        },
        {
            "url": "http://www.podtrac.com/pts/redirect.mp3/cdn.newrustacean.com/interview/rbr_2017/colin_dean.mp3",
            "downloaded": true,
            "title": "RBR 2017: Colin Dean",
            "published": 1510406568.0,
            "listened": false
        },
        {
            "url": "http://www.podtrac.com/pts/redirect.mp3/cdn.newrustacean.com/meta/_2.mp3",
            "downloaded": false,
            "title": "Meta 2: Two milestones",
            "published": 1506327635.0,
            "listened": false
        },
        {
            "url": "http://www.podtrac.com/pts/redirect.mp3/cdn.newrustacean.com/meta/_2.mp3",
            "downloaded": false,
            "title": "Meta 2: Two milestones",
            "published": 1506320435.0,
            "listened": false
        },
        {
            "url": "http://www.podtrac.com/pts/redirect.mp3/cdn.newrustacean.com/cysk/rayon.mp3",
            "downloaded": false,
            "title": "CYSK: Rayon",
            "published": 1505568300.0,
            "listened": false
        },
        {
            "url": "http://www.podtrac.com/pts/redirect.mp3/cdn.newrustacean.com/cysk/rayon.mp3",
            "downloaded": false,
            "title": "CYSK: Rayon",
            "published": 1505561100.0,
            "listened": false
        },
        {
            "url": "http://www.podtrac.com/pts/redirect.mp3/cdn.newrustacean.com/news/rust_1_20.mp3",
            "downloaded": false,
            "title": "News: Rust 1.20",
            "published": 1504215000.0,
            "listened": false
        },
        {
            "url": "http://www.podtrac.com/pts/redirect.mp3/cdn.newrustacean.com/news/rust_1_20.mp3",
            "downloaded": false,
            "title": "News: Rust 1.20",
            "published": 1504207800.0,
            "listened": false
        },
        {
            "url": "http://www.podtrac.com/pts/redirect.mp3/cdn.newrustacean.com/bonus_9.mp3",
            "downloaded": false,
            "title": "Bonus 9: Open source is mostly just normal people",
            "published": 1502697600.0,
            "listened": false
        },
        {
            "url": "http://www.podtrac.com/pts/redirect.mp3/cdn.newrustacean.com/bonus_9.mp3",
            "downloaded": false,
            "title": "Bonus 9: Open source is mostly just normal people",
            "published": 1502690400.0,
            "listened": false
        },
        {
            "url": "http://www.podtrac.com/pts/redirect.mp3/cdn.newrustacean.com/e021.mp3",
            "downloaded": false,
            "title": "e021: Keeping your types under cover",
            "published": 1500320100.0,
            "listened": false
        },
        {
            "url": "http://www.podtrac.com/pts/redirect.mp3/cdn.newrustacean.com/e021.mp3",
            "downloaded": false,
            "title": "e021: Keeping your types under cover",
            "published": 1500312900.0,
            "listened": false
        },
        {
            "url": "http://www.podtrac.com/pts/redirect.mp3/cdn.newrustacean.com/news_3.mp3",
            "downloaded": false,
            "title": "News 3: Increasing Rust's Reach",
            "published": 1499180400.0,
            "listened": false
        },
        {
            "url": "http://www.podtrac.com/pts/redirect.mp3/cdn.newrustacean.com/news_3.mp3",
            "downloaded": false,
            "title": "News 3: Increasing Rust's Reach",
            "published": 1499173200.0,
            "listened": false
        },
        {
            "url": "http://www.podtrac.com/pts/redirect.mp3/cdn.newrustacean.com/cysk_rocket.mp3",
            "downloaded": false,
            "title": "CYSK: Rocket",
            "published": 1498856400.0,
            "listened": false
        },
        {
            "url": "http://www.podtrac.com/pts/redirect.mp3/cdn.newrustacean.com/cysk_rocket.mp3",
            "downloaded": false,
            "title": "CYSK: Rocket",
            "published": 1498849200.0,
            "listened": false
        },
        {
            "url": "http://www.podtrac.com/pts/redirect.mp3/cdn.newrustacean.com/interview_4_part_3.mp3",
            "downloaded": false,
            "title": "Interview 4 \u2013 Jonathan Turner: Part 3",
            "published": 1497710850.0,
            "listened": false
        },
        {
            "url": "http://www.podtrac.com/pts/redirect.mp3/cdn.newrustacean.com/interview_4_part_3.mp3",
            "downloaded": false,
            "title": "Interview 4 \u2013 Jonathan Turner: Part 3",
            "published": 1497703650.0,
            "listened": false
        },
        {
            "url": "http://www.podtrac.com/pts/redirect.mp3/cdn.newrustacean.com/interview_4_part_2.mp3",
            "downloaded": false,
            "title": "Interview 4 \u2013 Jonathan Turner: Part 2",
            "published": 1496158588.0,
            "listened": false
        },
        {
            "url": "http://www.podtrac.com/pts/redirect.mp3/cdn.newrustacean.com/interview_4_part_2.mp3",
            "downloaded": false,
            "title": "Interview 4 \u2013 Jonathan Turner: Part 2",
            "published": 1496151388.0,
            "listened": false
        },
        {
            "url": "http://www.podtrac.com/pts/redirect.mp3/cdn.newrustacean.com/interview_4_part_1.mp3",
            "downloaded": false,
            "title": "Interview 4 \u2013 Jonathan Turner: Part 1",
            "published": 1493586786.0,
            "listened": false
        },
        {
            "url": "http://www.podtrac.com/pts/redirect.mp3/cdn.newrustacean.com/interview_4_part_1.mp3",
            "downloaded": false,
            "title": "Interview 4 \u2013 Jonathan Turner: Part 1",
            "published": 1493579586.0,
            "listened": false
        },
        {
            "url": "http://www.podtrac.com/pts/redirect.mp3/cdn.newrustacean.com/cysk_3.mp3",
            "downloaded": false,
            "title": "CYSK: RLS",
            "published": 1492521457.0,
            "listened": false
        },
        {
            "url": "http://www.podtrac.com/pts/redirect.mp3/cdn.newrustacean.com/cysk_3.mp3",
            "downloaded": false,
            "title": "CYSK: RLS",
            "published": 1492514257.0,
            "listened": false
        },
        {
            "url": "http://www.podtrac.com/pts/redirect.mp3/cdn.newrustacean.com/e020.mp3",
            "downloaded": false,
            "title": "e020: Putting code in its place",
            "published": 1491053913.0,
            "listened": false
        },
        {
            "url": "http://www.podtrac.com/pts/redirect.mp3/cdn.newrustacean.com/e020.mp3",
            "downloaded": false,
            "title": "e020: Putting code in its place",
            "published": 1491046713.0,
            "listened": false
        },
        {
            "url": "http://www.podtrac.com/pts/redirect.mp3/cdn.newrustacean.com/bonus_8.mp3",
            "downloaded": false,
            "title": "Bonus 8: Giving back (by teaching)",
            "published": 1489921200.0,
            "listened": false
        },
        {
            "url": "http://www.podtrac.com/pts/redirect.mp3/cdn.newrustacean.com/bonus_8.mp3",
            "downloaded": false,
            "title": "Bonus 8: Giving back (by teaching)",
            "published": 1489914000.0,
            "listened": false
        },
        {
            "url": "http://www.podtrac.com/pts/redirect.mp3/cdn.newrustacean.com/e019.mp3",
            "downloaded": false,
            "title": "e019: Let's `Clone` a `Cow`",
            "published": 1488302400.0,
            "listened": false
        },
        {
            "url": "http://www.podtrac.com/pts/redirect.mp3/cdn.newrustacean.com/e019.mp3",
            "downloaded": false,
            "title": "e019: Let's `Clone` a `Cow`",
            "published": 1488295200.0,
            "listened": false
        },
        {
            "url": "http://www.podtrac.com/pts/redirect.mp3/cdn.newrustacean.com/cysk_2.mp3",
            "downloaded": false,
            "title": "CYSK: clap",
            "published": 1487108011.0,
            "listened": false
        },
        {
            "url": "http://www.podtrac.com/pts/redirect.mp3/cdn.newrustacean.com/cysk_2.mp3",
            "downloaded": false,
            "title": "CYSK: clap",
            "published": 1487100811.0,
            "listened": false
        },
        {
            "url": "http://www.podtrac.com/pts/redirect.mp3/cdn.newrustacean.com/e018.mp3",
            "downloaded": false,
            "title": "e018: `Borrow`, `AsRef`, `Deref`: my head hurts now",
            "published": 1485887543.0,
            "listened": false
        },
        {
            "url": "http://www.podtrac.com/pts/redirect.mp3/cdn.newrustacean.com/e018.mp3",
            "downloaded": false,
            "title": "e018: `Borrow`, `AsRef`, `Deref`: my head hurts now",
            "published": 1485880343.0,
            "listened": false
        },
        {
            "url": "http://www.podtrac.com/pts/redirect.mp3/cdn.newrustacean.com/csyk_1.mp3",
            "downloaded": false,
            "title": "CYSK: quick-xml",
            "published": 1483952601.0,
            "listened": false
        },
        {
            "url": "http://www.podtrac.com/pts/redirect.mp3/cdn.newrustacean.com/csyk_1.mp3",
            "downloaded": false,
            "title": "CYSK: quick-xml",
            "published": 1483945401.0,
            "listened": false
        },
        {
            "url": "http://www.podtrac.com/pts/redirect.mp3/cdn.newrustacean.com/news_2.mp3",
            "downloaded": false,
            "title": "News 2: Let's talk roadmap!",
            "published": 1483020000.0,
            "listened": false
        },
        {
            "url": "http://www.podtrac.com/pts/redirect.mp3/cdn.newrustacean.com/news_2.mp3",
            "downloaded": false,
            "title": "News 2: Let's talk roadmap!",
            "published": 1483012800.0,
            "listened": false
        },
        {
            "url": "http://www.podtrac.com/pts/redirect.mp3/cdn.newrustacean.com/meta_1.mp3",
            "downloaded": false,
            "title": "Meta 1 \u2013 Slowing Down",
            "published": 1478957216.0,
            "listened": false
        },
        {
            "url": "http://www.podtrac.com/pts/redirect.mp3/cdn.newrustacean.com/meta_1.mp3",
            "downloaded": false,
            "title": "Meta 1 \u2013 Slowing Down",
            "published": 1478950016.0,
            "listened": false
        },
        {
            "url": "http://www.podtrac.com/pts/redirect.mp3/cdn.newrustacean.com/interview_3.mp3",
            "downloaded": false,
            "title": "Interview 3 \u2013 Carol (Nichols || Goulding)",
            "published": 1475218800.0,
            "listened": false
        },
        {
            "url": "http://www.podtrac.com/pts/redirect.mp3/cdn.newrustacean.com/interview_3.mp3",
            "downloaded": false,
            "title": "Interview 3 \u2013 Carol (Nichols || Goulding)",
            "published": 1475211600.0,
            "listened": false
        },
        {
            "url": "http://www.podtrac.com/pts/redirect.mp3/cdn.newrustacean.com/bonus_7.mp3",
            "downloaded": false,
            "title": "Bonus 7: Katas\u2014or: learning by doing",
            "published": 1473511819.0,
            "listened": false
        },
        {
            "url": "http://www.podtrac.com/pts/redirect.mp3/cdn.newrustacean.com/bonus_7.mp3",
            "downloaded": false,
            "title": "Bonus 7: Katas\u2014or: learning by doing",
            "published": 1473504619.0,
            "listened": false
        },
        {
            "url": "http://www.podtrac.com/pts/redirect.mp3/cdn.newrustacean.com/bonus_6.mp3",
            "downloaded": false,
            "title": "Bonus 6: It doesn\u2018t have to be sexy",
            "published": 1471691743.0,
            "listened": false
        },
        {
            "url": "http://www.podtrac.com/pts/redirect.mp3/cdn.newrustacean.com/bonus_6.mp3",
            "downloaded": false,
            "title": "Bonus 6: It doesn\u2018t have to be sexy",
            "published": 1471684543.0,
            "listened": false
        },
        {
            "url": "http://www.podtrac.com/pts/redirect.mp3/cdn.newrustacean.com/e017.mp3",
            "downloaded": false,
            "title": "e017: Point me where I need to go",
            "published": 1470670500.0,
            "listened": false
        },
        {
            "url": "http://www.podtrac.com/pts/redirect.mp3/cdn.newrustacean.com/e017.mp3",
            "downloaded": false,
            "title": "e017: Point me where I need to go",
            "published": 1470663300.0,
            "listened": false
        }
    ]
}